markdown_sub_sup.py
markdown_sub_sup-0.0.3.dist-info/LICENSE
markdown_sub_sup-0.0.3.dist-info/METADATA
markdown_sub_sup-0.0.3.dist-info/WHEEL
markdown_sub_sup-0.0.3.dist-info/top_level.txt
markdown_sub_sup-0.0.3.dist-info/RECORD
